audio2video/__init__.py
audio2video/__main__.py
audio2video/cli.py
audio2video-0.1.1.dist-info/licenses/LICENSE
audio2video-0.1.1.dist-info/METADATA
audio2video-0.1.1.dist-info/WHEEL
audio2video-0.1.1.dist-info/entry_points.txt
audio2video-0.1.1.dist-info/top_level.txt
audio2video-0.1.1.dist-info/RECORD
