Metadata-Version: 2.4
Name: audio2video
Version: 0.1.1
Summary: Convert audio files with static images to video format for YouTube and social media
Author-email: Kaoru Babasaki <kaorubabasaki@gmail.com>
License-Expression: MIT
Project-URL: Homepage, https://github.com/KaoruBB/audio2video
Project-URL: Documentation, https://github.com/KaoruBB/audio2video/wiki
Project-URL: Repository, https://github.com/KaoruBB/audio2video.git
Project-URL: Issues, https://github.com/KaoruBB/audio2video/issues
Keywords: audio,video,conversion,youtube,moviepy,podcast
Classifier: Development Status :: 4 - Beta
Classifier: Intended Audience :: Developers
Classifier: Intended Audience :: End Users/Desktop
Classifier: Operating System :: OS Independent
Classifier: Programming Language :: Python :: 3
Classifier: Programming Language :: Python :: 3.9
Classifier: Programming Language :: Python :: 3.10
Classifier: Programming Language :: Python :: 3.11
Classifier: Programming Language :: Python :: 3.12
Classifier: Topic :: Multimedia :: Video :: Conversion
Classifier: Topic :: Software Development :: Libraries :: Python Modules
Requires-Python: >=3.9
License-File: LICENSE
Requires-Dist: moviepy>=2.2.1
Dynamic: license-file
